{
    "p": {
        "name": "voiceless bilabial plosive",
        "place_group": "bilabial",
        "manner_group": "plosive",
        "features": {
            "syllabic": "-",
            "consonantal": "+",
            "sonorant": "-",
            "continuant": "-",
            "delayed release": "-",
            "approximant": "-",
            "tap": "-",
            "trill": "-",
            "nasal": "-",
            "voice": "-",
            "spread glottis": "-",
            "constricted glottis": "-",
            "labial": "+",
            "round": "-",
            "labiodental": "-",            
            "coronal": "-",
            "anterior": "0",
            "distributed": "0",
            "strident": "0",
            "lateral": "-",
            "dorsal": "-",
            "high": "0",
            "low": "0",
            "front": "0",
            "back": "0",
            "tense": "0"
        }    
    },
    "b": {
        "name": "voiced bilabial stop",
        "place_group": "bilabial",
        "manner_group": "plosive",
        "features": {            
            "syllabic": "-",
            "consonantal": "+",
            "sonorant": "-",
            "continuant": "-",
            "delayed release": "-",
            "approximant": "-",
            "tap": "-",
            "trill": "-",
            "nasal": "-",
            "voice": "+",
            "spread glottis": "-",
            "constricted glottis": "-",
            "labial": "+",
            "round": "-",
            "labiodental": "-",            
            "coronal": "-",
            "anterior": "0",
            "distributed": "0",
            "strident": "0",
            "lateral": "-",
            "dorsal": "-",
            "high": "0",
            "low": "0",
            "front": "0",
            "back": "0",
            "tense": "0"
        }
    },
    "ɸ": {
        "name": "voiceless bilabial fricative",
        "place_group": "bilabial",
        "manner_group": "fricative",
        "features": {
            "syllabic": "-",
            "consonantal": "+",
            "sonorant": "-",
            "continuant": "+",
            "delayed release": "+",
            "approximant": "-",
            "tap": "-",
            "trill": "-",
            "nasal": "-",
            "voice": "-",
            "spread glottis": "-",
            "constricted glottis": "-",
            "labial": "+",
            "round": "-",
            "labiodental": "-",            
            "coronal": "-",
            "anterior": "0",
            "distributed": "0",
            "strident": "0",
            "lateral": "-",
            "dorsal": "-",
            "high": "0",
            "low": "0",
            "front": "0",
            "back": "0",
            "tense": "0"
        }
    },
    "β": {
        "name": "voiced bilabial fricative",
        "place_group": "bilabial",
        "manner_group": "fricative",
        "features": {
            "syllabic": "-",
            "consonantal": "+",
            "sonorant": "-",
            "continuant": "+",
            "delayed release": "+",
            "approximant": "-",
            "tap": "-",
            "trill": "-",
            "nasal": "-",
            "voice": "+",
            "spread glottis": "-",
            "constricted glottis": "-",
            "labial": "+",
            "round": "-",
            "labiodental": "-",            
            "coronal": "-",
            "anterior": "0",
            "distributed": "0",
            "strident": "0",
            "lateral": "-",
            "dorsal": "-",
            "high": "0",
            "low": "0",
            "front": "0",
            "back": "0",
            "tense": "0"
        }
    },
    "m": {
        "name": "bilabial nasal",
        "place_group": "bilabial",
        "manner_group": "nasal",
        "features": {
            "syllabic": "-",
            "consonantal": "+",
            "sonorant": "+",
            "continuant": "-",
            "delayed release": "0",
            "approximant": "-",
            "tap": "-",
            "trill": "-",
            "nasal": "+",
            "voice": "+",
            "spread glottis": "-",
            "constricted glottis": "-",
            "labial": "+",
            "round": "-",
            "labiodental": "-",            
            "coronal": "-",
            "anterior": "0",
            "distributed": "0",
            "strident": "0",
            "lateral": "-",
            "dorsal": "-",
            "high": "0",
            "low": "0",
            "front": "0",
            "back": "0",
            "tense": "0"
        }
    },
    "ʙ": {
        "name": "voiced bilabial trill",
        "place_group": "bilabial",
        "manner_group": "trill",
        "features": {
            "syllabic": "-",
            "consonantal": "+",
            "sonorant": "+",
            "continuant": "+",
            "delayed release": "0",
            "approximant": "+",
            "tap": "-",
            "trill": "+",
            "nasal": "-",
            "voice": "+",
            "spread glottis": "-",
            "constricted glottis": "-",
            "labial": "+",
            "round": "-",
            "labiodental": "-",            
            "coronal": "-",
            "anterior": "0",
            "distributed": "0",
            "strident": "0",
            "lateral": "-",
            "dorsal": "-",
            "high": "0",
            "low": "0",
            "front": "0",
            "back": "0",
            "tense": "0"
        }
    },
    "pf": {
        "name": "voiceless labiodental affricate",
        "place_group": "labiodental",
        "manner_group": "affricate",
        "features": {
            "syllabic": "-",
            "consonantal": "+",
            "sonorant": "-",
            "continuant": "-",
            "delayed release": "+",
            "approximant": "-",
            "tap": "-",
            "trill": "-",
            "nasal": "-",
            "voice": "-",
            "spread glottis": "-",
            "constricted glottis": "-",
            "labial": "+",
            "round": "-",
            "labiodental": "+",            
            "coronal": "-",
            "anterior": "0",
            "distributed": "0",
            "strident": "0",
            "lateral": "-",
            "dorsal": "-",
            "high": "0",
            "low": "0",
            "front": "0",
            "back": "0",
            "tense": "0"
        }
    },
    "f": {
        "name": "voiceless labiodental fricative",
        "place_group": "labiodental",
        "manner_group": "fricative",
        "features": {
            "syllabic": "-",
            "consonantal": "+",
            "sonorant": "-",
            "continuant": "+",
            "delayed release": "+",
            "approximant": "-",
            "tap": "-",
            "trill": "-",
            "nasal": "-",
            "voice": "-",
            "spread glottis": "-",
            "constricted glottis": "-",
            "labial": "+",
            "round": "-",
            "labiodental": "+",            
            "coronal": "-",
            "anterior": "0",
            "distributed": "0",
            "strident": "0",
            "lateral": "-",
            "dorsal": "-",
            "high": "0",
            "low": "0",
            "front": "0",
            "back": "0",
            "tense": "0"
        }
    },
    "v": {
        "name": "voiced labiodental fricative",
        "place_group": "labiodental",
        "manner_group": "fricative",
        "features": {
            "syllabic": "-",
            "consonantal": "+",
            "sonorant": "-",
            "continuant": "+",
            "delayed release": "+",
            "approximant": "-",
            "tap": "-",
            "trill": "-",
            "nasal": "-",
            "voice": "+",
            "spread glottis": "-",
            "constricted glottis": "-",
            "labial": "+",
            "round": "-",
            "labiodental": "+",            
            "coronal": "-",
            "anterior": "0",
            "distributed": "0",
            "strident": "0",
            "lateral": "-",
            "dorsal": "-",
            "high": "0",
            "low": "0",
            "front": "0",
            "back": "0",
            "tense": "0"
        }
    },
    "ɱ": {
        "name": "labiodental nasal",
        "place_group": "labiodental",
        "manner_group": "nasal",
        "features": {
            "syllabic": "-",
            "consonantal": "+",
            "sonorant": "+",
            "continuant": "-",
            "delayed release": "0",
            "approximant": "-",
            "tap": "-",
            "trill": "-",
            "nasal": "+",
            "voice": "+",
            "spread glottis": "-",
            "constricted glottis": "-",
            "labial": "+",
            "round": "-",
            "labiodental": "+",           
            "coronal": "-",
            "anterior": "0",
            "distributed": "0",
            "strident": "0",
            "lateral": "-",
            "dorsal": "-",
            "high": "0",
            "low": "0",
            "front": "0",
            "back": "0",
            "tense": "0"
        }
    },
    "ʋ": {
        "name": "labiodental approximant",
        "place_group": "labiodental",
        "manner_group": "approximant",
        "features": {
            "syllabic": "-",
            "consonantal": "-",
            "sonorant": "+",
            "continuant": "+",
            "delayed release": "0",
            "approximant": "+",
            "tap": "-",
            "trill": "-",
            "nasal": "-",
            "voice": "+",
            "spread glottis": "-",
            "constricted glottis": "-",
            "labial": "+",
            "round": "-",
            "labiodental": "+",           
            "coronal": "-",
            "anterior": "0",
            "distributed": "0",
            "strident": "0",
            "lateral": "-",
            "dorsal": "-",
            "high": "0",
            "low": "0",
            "front": "0",
            "back": "0",
            "tense": "0"
        }
    },
    "t̪": {
        "name": "voiceless dental plosive",
        "place_group": "dental",
        "manner_group": "plosive",
        "features": {
            "syllabic": "-",
            "consonantal": "+",
            "sonorant": "-",
            "continuant": "-",
            "delayed release": "-",
            "approximant": "-",
            "tap": "-",
            "trill": "-",
            "nasal": "-",
            "voice": "-",
            "spread glottis": "-",
            "constricted glottis": "-",
            "labial": "-",
            "round": "-",
            "labiodental": "-",           
            "coronal": "+",
            "anterior": "+",
            "distributed": "+",
            "strident": "-",
            "lateral": "-",
            "dorsal": "-",
            "high": "0",
            "low": "0",
            "front": "0",
            "back": "0",
            "tense": "0"
        }
    },
    "d̪": {
        "name": "voiced dental plosive",
        "place_group": "dental",
        "manner_group": "plosive",
        "features": {
            "syllabic": "-",
            "consonantal": "+",
            "sonorant": "-",
            "continuant": "-",
            "delayed release": "-",
            "approximant": "-",
            "tap": "-",
            "trill": "-",
            "nasal": "-",
            "voice": "+",
            "spread glottis": "-",
            "constricted glottis": "-",
            "labial": "-",
            "round": "-",
            "labiodental": "-",           
            "coronal": "+",
            "anterior": "+",
            "distributed": "+",
            "strident": "-",
            "lateral": "-",
            "dorsal": "-",
            "high": "0",
            "low": "0",
            "front": "0",
            "back": "0",
            "tense": "0"
        }
    },
    "θ": {
        "name": "voiceless dental fricative",
        "place_group": "dental",
        "manner_group": "fricative",
        "features": {
            "syllabic": "-",
            "consonantal": "+",
            "sonorant": "-",
            "continuant": "+",
            "delayed release": "+",
            "approximant": "-",
            "tap": "-",
            "trill": "-",
            "nasal": "-",
            "voice": "-",
            "spread glottis": "-",
            "constricted glottis": "-",
            "labial": "-",
            "round": "-",
            "labiodental": "-",           
            "coronal": "+",
            "anterior": "+",
            "distributed": "+",
            "strident": "-",
            "lateral": "-",
            "dorsal": "-",
            "high": "0",
            "low": "0",
            "front": "0",
            "back": "0",
            "tense": "0"
        }
    },
    "ð": {
        "name": "voiced dental fricative",
        "place_group": "dental",
        "manner_group": "fricative",
        "features": {
            "syllabic": "-",
            "consonantal": "+",
            "sonorant": "-",
            "continuant": "+",
            "delayed release": "+",
            "approximant": "-",
            "tap": "-",
            "trill": "-",
            "nasal": "-",
            "voice": "+",
            "spread glottis": "-",
            "constricted glottis": "-",
            "labial": "-",
            "round": "-",
            "labiodental": "-",           
            "coronal": "+",
            "anterior": "+",
            "distributed": "+",
            "strident": "-",
            "lateral": "-",
            "dorsal": "-",
            "high": "0",
            "low": "0",
            "front": "0",
            "back": "0",
            "tense": "0"
        }
    },
    "t": {
        "name": "voiceless alveolar plosive",
        "place_group": "alveolar",
        "manner_group": "plosive",
        "features": {
            "syllabic": "-",
            "consonantal": "+",
            "sonorant": "-",
            "continuant": "-",
            "delayed release": "-",
            "approximant": "-",
            "tap": "-",
            "trill": "-",
            "nasal": "-",
            "voice": "-",
            "spread glottis": "-",
            "constricted glottis": "-",
            "labial": "-",
            "round": "-",
            "labiodental": "-",           
            "coronal": "+",
            "anterior": "+",
            "distributed": "-",
            "strident": "-",
            "lateral": "-",
            "dorsal": "-",
            "high": "0",
            "low": "0",
            "front": "0",
            "back": "0",
            "tense": "0"
        }
    },
    "d": {
        "name": "voiced alveolar plosive",
        "place_group": "alveolar",
        "manner_group": "plosive",
        "features": {
            "syllabic": "-",
            "consonantal": "+",
            "sonorant": "-",
            "continuant": "-",
            "delayed release": "-",
            "approximant": "-",
            "tap": "-",
            "trill": "-",
            "nasal": "-",
            "voice": "+",
            "spread glottis": "-",
            "constricted glottis": "-",
            "labial": "-",
            "round": "-",
            "labiodental": "-",           
            "coronal": "+",
            "anterior": "+",
            "distributed": "-",
            "strident": "-",
            "lateral": "-",
            "dorsal": "-",
            "high": "0",
            "low": "0",
            "front": "0",
            "back": "0",
            "tense": "0"
        }
    }
}